MANIFEST.in
README
README.rst
amqp2amqp_identvalidationd
amqp2amqp_json2bufrd
amqp2arkimetd
amqp2dballed
amqp2djangod
amqp2geoimaged
amqp2mqttd
composereportd
dashboard.conf
dballe2arkimet
dumpstation.py
graphTemplates.conf
main.py
manage.py
map
mqtt2dballed
mqtt2graphited
poweroffd
rmap-configure
rmap-site.cfg
rmap.cfg
rmap.wsgi
rmapctrl
rmapgui
rmapweb
setup.py
sign.sh
station_jsonrpc.py
stationd
amatyr/__init__.py
amatyr/admin.py
amatyr/models.py
amatyr/urls.py
amatyr/views.py
amatyr/migrations/__init__.py
amatyr/static/amatyr/screen.css
amatyr/static/amatyr/js/amatyr.js
amatyr/static/amatyr/js/amatyrlib.js
amatyr/static/amatyr/js/d3.v3.min.js
amatyr/static/amatyr/js/drawbars.js
amatyr/static/amatyr/js/drawline.js
amatyr/static/amatyr/js/path.min.js
amatyr/static/amatyr/js/rivets.min.js
amatyr/static/amatyr/js/sparkline.js
amatyr/static/amatyr/js/temprain.js
amatyr/static/amatyr/js/timelinegraph.js
amatyr/static/amatyr/js/watch.js
amatyr/static/amatyr/js/windrose.js
amatyr/templates/amatyr/cam.html
amatyr/templates/amatyr/dashbar.html
amatyr/templates/amatyr/index.html
borinud/__init__.py
borinud/admin.py
borinud/models.py
borinud/settings.py
borinud/tests.py
borinud/urls.py
borinud/views.py
borinud/migrations/__init__.py
borinud/static/borinud/borinud-client.js
borinud/static/borinud/borinud.B.js
borinud/static/borinud/borinud.level.js
borinud/static/borinud/borinud.trange.js
borinud/templates/borinud/map.html
borinud/utils/__init__.py
borinud/utils/codec.py
borinud/utils/source.py
borinud/v1/__init__.py
borinud/v1/tests.py
borinud/v1/urls.py
borinud/v1/utils.py
borinud/v1/views.py
borinud_sos/__init__.py
borinud_sos/admin.py
borinud_sos/apps.py
borinud_sos/models.py
borinud_sos/tests.py
borinud_sos/urls.py
borinud_sos/views.py
borinud_sos/migrations/__init__.py
borinud_sos/templates/borinud_sos/xml/1.0/DescribeSensor.xml
borinud_sos/templates/borinud_sos/xml/1.0/GetCapabilities.xml
borinud_sos/templates/borinud_sos/xml/1.0/GetObservation.xml
doc/README
rmap.egg-info/PKG-INFO
rmap.egg-info/SOURCES.txt
rmap.egg-info/dependency_links.txt
rmap.egg-info/requires.txt
rmap.egg-info/top_level.txt
