Metadata-Version: 1.0
Name: rmap
Version: 7.5
Summary: rete monitoraggio ambientale partecipativo
Home-page: https://github.com/r-map/rmap
Author: Paolo Patruno
Author-email: p.patruno@iperbole.bologna.it
License: GNU GPL v2
Platform: any
